generateur_app_django/__init__.py
generateur_app_django/__main__.py
generateur_app_django/main.py
generateur_app_django-0.1.0.dist-info/METADATA
generateur_app_django-0.1.0.dist-info/WHEEL
generateur_app_django-0.1.0.dist-info/entry_points.txt
generateur_app_django-0.1.0.dist-info/top_level.txt
generateur_app_django-0.1.0.dist-info/RECORD
